services/__init__.py
services/configuration_app.py
turtle_glide/__init__.py
turtle_glide/management/__init__.py
turtle_glide/management/commands/__init__.py
turtle_glide/management/commands/create_app.py
turtle_glide/management/commands/create_archive.py
turtle_glide-2.2.1.dist-info/licenses/LICENSE
utils/__init__.py
utils/helpers_command_global.py
utils/styles_variables.py
utils/variable_globals.py
turtle_glide-2.2.1.dist-info/METADATA
turtle_glide-2.2.1.dist-info/WHEEL
turtle_glide-2.2.1.dist-info/top_level.txt
turtle_glide-2.2.1.dist-info/RECORD
