Metadata-Version: 2.4
Name: turtle_glide
Version: 2.2.1
Summary: Librería para commandos para django
Author-email: Alejandro <hjosealejandro21@gmail.com>
License: MPL-2.0
Project-URL: repository, https://github.com/jose-CR/TurtleGlide
Classifier: Environment :: Console
Classifier: Intended Audience :: Developers
Classifier: Operating System :: OS Independent
Classifier: Programming Language :: Python :: 3
Classifier: License :: OSI Approved :: Mozilla Public License 2.0 (MPL 2.0)
License-File: LICENSE
Requires-Dist: requests
Requires-Dist: django>=3.2
Dynamic: license-file
